robloxmemoryapi/__init__.py
robloxmemoryapi/utils/__init__.py
robloxmemoryapi/utils/memory.py
robloxmemoryapi/utils/offsets.py
robloxmemoryapi/utils/luau/__init__.py
robloxmemoryapi/utils/luau/parser.py
robloxmemoryapi/utils/rbx/__init__.py
robloxmemoryapi/utils/rbx/datastructures.py
robloxmemoryapi/utils/rbx/instance.py
robloxmemoryapi/utils/rbx/bytecode/decryptor.py
robloxmemoryapi/utils/rbx/bytecode/encryptor.py
robloxmemoryapi-0.1.7.dist-info/licenses/LICENSE.md
robloxmemoryapi-0.1.7.dist-info/METADATA
robloxmemoryapi-0.1.7.dist-info/WHEEL
robloxmemoryapi-0.1.7.dist-info/top_level.txt
robloxmemoryapi-0.1.7.dist-info/RECORD
