Metadata-Version: 2.4
Name: robloxmemoryapi
Version: 0.1.7
Summary: Python Library that abstracts reading and writing data from the Roblox DataModel
Author-email: upio <notpoiu@users.noreply.github.com>, mstudio45 <mstudio45@users.noreply.github.com>, ActualMasterOogway <ActualMasterOogway@users.noreply.github.com>
License: Copyright 2025 upio, mstudio45, master oogway
Project-URL: Homepage, https://github.com/notpoiu/RobloxMemoryAPI
Project-URL: Issues, https://github.com/notpoiu/RobloxMemoryAPI/issues
Keywords: roblox,memory,windows
Classifier: Programming Language :: Python :: 3
Classifier: License :: OSI Approved :: MIT License
Classifier: Operating System :: Microsoft :: Windows
Classifier: Development Status :: 3 - Alpha
Classifier: Intended Audience :: Developers
Classifier: Topic :: Software Development :: Libraries
Requires-Python: >=3.9
License-File: LICENSE.md
Requires-Dist: requests>=2.0
Requires-Dist: zstandard>=0.19.0
Requires-Dist: xxhash>=3.6.0
Requires-Dist: blake3>=1.0.8
Dynamic: license-file
